README.rst
setup.py
py_easy_async/__init__.py
py_easy_async/process.py
py_easy_async.egg-info/PKG-INFO
py_easy_async.egg-info/SOURCES.txt
py_easy_async.egg-info/dependency_links.txt
py_easy_async.egg-info/top_level.txt