Metadata-Version: 1.1
Name: py-easy-async
Version: 0.1
Summary: Provides simple interface for threading to easy perform async actions
Home-page: https://github.com/aka-toxa/py_easy_async
Author: Petrovskyi Anatolii
Author-email: inbox@toxa.io
License: MIT
Platform: UNKNOWN
Classifier: License :: OSI Approved :: MIT License
Classifier: Intended Audience :: Developers
Classifier: Programming Language :: Python :: 3.4
Classifier: Programming Language :: Python :: 3.5
Classifier: Topic :: Software Development :: Libraries
Classifier: Development Status :: 4 - Beta
